wait_for_it/__init__.py
wait_for_it/__main__.py
wait_for_it/test_wait_for_it.py
wait_for_it/wait_for_it.py
wait_for_it-2.2.2.dist-info/LICENSE
wait_for_it-2.2.2.dist-info/METADATA
wait_for_it-2.2.2.dist-info/WHEEL
wait_for_it-2.2.2.dist-info/entry_points.txt
wait_for_it-2.2.2.dist-info/top_level.txt
wait_for_it-2.2.2.dist-info/RECORD
