Metadata-Version: 2.1
Name: wait-for-it
Version: 2.2.2
Summary: Wait for service(s) to be available before executing a command.
Home-page: https://github.com/clarketm/wait-for-it
Author: Travis Clarke
Author-email: travis.m.clarke@gmail.com
Classifier: Programming Language :: Python :: 3
Classifier: Programming Language :: Python :: 3 :: Only
Classifier: Programming Language :: Python :: 3.7
Classifier: Programming Language :: Python :: 3.8
Classifier: Programming Language :: Python :: 3.9
Classifier: Programming Language :: Python :: 3.10
Classifier: Programming Language :: Python :: 3.11
Classifier: License :: OSI Approved :: MIT License
Classifier: Operating System :: POSIX
Classifier: Topic :: Internet
Classifier: Topic :: Utilities
Requires-Python: >=3.7
License-File: LICENSE
Requires-Dist: click
Provides-Extra: dev
Requires-Dist: black ; extra == 'dev'
Requires-Dist: click ; extra == 'dev'
Requires-Dist: flake8 ; extra == 'dev'
Requires-Dist: parameterized ; extra == 'dev'
Requires-Dist: pytest ; extra == 'dev'
Requires-Dist: pytest-cov ; extra == 'dev'
Requires-Dist: twine ; extra == 'dev'
